codepost/__init__.py
codepost/api_requestor.py
codepost/errors.py
codepost/http_client.py
codepost/instantiated.py
codepost/version.py
codepost/models/__init__.py
codepost/models/assignments.py
codepost/models/comments.py
codepost/models/course_rosters.py
codepost/models/courses.py
codepost/models/file_templates.py
codepost/models/files.py
codepost/models/rubric_categories.py
codepost/models/rubric_comments.py
codepost/models/sections.py
codepost/models/submission_tests.py
codepost/models/submissions.py
codepost/models/test_cases.py
codepost/models/test_categories.py
codepost/models/abstract/__init__.py
codepost/models/abstract/api_crud.py
codepost/models/abstract/api_resource.py
codepost/models/abstract/api_resource_metaclass.py
codepost/models/abstract/lazy.py
codepost/models/abstract/linked_lists.py
codepost/util/__init__.py
codepost/util/config.py
codepost/util/custom_logging.py
codepost/util/helpers.py
codepost/util/misc.py
codepost-0.3.2.dist-info/LICENSE
codepost-0.3.2.dist-info/METADATA
codepost-0.3.2.dist-info/WHEEL
codepost-0.3.2.dist-info/top_level.txt
codepost-0.3.2.dist-info/RECORD
