Metadata-Version: 2.1
Name: codepost
Version: 0.3.2
Summary: Python bindings for the codePost API
Home-page: https://github.com/codepost-io/codepost-python
Author: codePost
Author-email: team@codepost.io
License: MIT
Classifier: License :: OSI Approved :: MIT License
Classifier: Programming Language :: Python :: 3
Classifier: Programming Language :: Python :: 3.7
License-File: LICENSE
Requires-Dist: requests
Requires-Dist: PyYAML
Requires-Dist: blessings
Requires-Dist: colorama
Requires-Dist: eliot
Requires-Dist: six
Requires-Dist: typing
Requires-Dist: enum34 ; python_version < "3.4"
Requires-Dist: python-forge ; python_version > "3.5"
